HMautogroup/__init__.py
HMautogroup/cleaning.py
HMautogroup/filter_list.py
HMautogroup/handler.py
HMautogroup/main.py
HMautogroup/similarity.py
HMautogroup/text_processing.py
HMautogroup-0.4.1.dist-info/LICENSE
HMautogroup-0.4.1.dist-info/METADATA
HMautogroup-0.4.1.dist-info/WHEEL
HMautogroup-0.4.1.dist-info/entry_points.txt
HMautogroup-0.4.1.dist-info/top_level.txt
HMautogroup-0.4.1.dist-info/RECORD
