Metadata-Version: 2.1
Name: HMautogroup
Version: 0.4.1
Summary: auto-cleaning-grouping-process
Home-page: https://github.com/kdpark0284/HM_titledescription_filtering
Author: KDPark
Author-email: k602511@gmail.com
Project-URL: Bug Tracker, https://github.com/kdpark0284/HM_titledescription_filtering/issues
Classifier: Programming Language :: Python :: 3
Classifier: License :: OSI Approved :: MIT License
Classifier: Operating System :: OS Independent
Requires-Python: >=3.10
License-File: LICENSE
Requires-Dist: openpyxl
Requires-Dist: numpy
Requires-Dist: pandas
Requires-Dist: regex
Requires-Dist: konlpy
Requires-Dist: setuptools
Requires-Dist: mecab-python
Requires-Dist: mecab-python3
Requires-Dist: rapidfuzz
Requires-Dist: jamo
Requires-Dist: wheel
